panshi_base/__init__.py
panshi_base/component/__init__.py
panshi_base/component/api_embedding_component.py
panshi_base/component/es_component.py
panshi_base/component/milvus_component.py
panshi_base/component/minio_component.py
panshi_base/component/mq_component.py
panshi_base/component/mysql_component.py
panshi_base/errors.py
panshi_base/langchain/__init__.py
panshi_base/langchain/embeddings/__init__.py
panshi_base/langchain/embeddings/panshi_embedding.py
panshi_base/langchain/vectorstores/__init__.py
panshi_base/langchain/vectorstores/panshi_milvus.py
panshi_base/model/__init__.py
panshi_base/model/chat_model.py
panshi_base/model/response.py
panshi_base/util/__init__.py
panshi_base/util/helper.py
panshi_base-0.1.19.dist-info/METADATA
panshi_base-0.1.19.dist-info/WHEEL
panshi_base-0.1.19.dist-info/RECORD
