Metadata-Version: 2.1
Name: panshi-base
Version: 0.1.19
Summary: 
Author: dengwenjie
Author-email: dengwenjie@numgal.com
Requires-Python: >3.7,<4
Classifier: Programming Language :: Python :: 3
Classifier: Programming Language :: Python :: 3.8
Classifier: Programming Language :: Python :: 3.9
Classifier: Programming Language :: Python :: 3.10
Classifier: Programming Language :: Python :: 3.11
Requires-Dist: loguru (>=0.7.2,<0.8.0)
Requires-Dist: pydantic (>=2.0.0,<3.0.0)
